main.py
mcp_gaode_weather_server_unique-0.1.0.dist-info/METADATA
mcp_gaode_weather_server_unique-0.1.0.dist-info/WHEEL
mcp_gaode_weather_server_unique-0.1.0.dist-info/entry_points.txt
mcp_gaode_weather_server_unique-0.1.0.dist-info/top_level.txt
mcp_gaode_weather_server_unique-0.1.0.dist-info/RECORD
