Metadata-Version: 2.4
Name: mcp-gaode-weather-server-unique
Version: 0.1.0
Summary: 输入Gaode api_key，获取天气信息
Requires-Python: >=3.11
Requires-Dist: httpx>=0.28.1
Requires-Dist: mcp>=1.6.0
Requires-Dist: numpy>=2.2.5
